picbed_smtp.py
picbed_smtp-0.1.3.dist-info/LICENSE
picbed_smtp-0.1.3.dist-info/METADATA
picbed_smtp-0.1.3.dist-info/WHEEL
picbed_smtp-0.1.3.dist-info/top_level.txt
picbed_smtp-0.1.3.dist-info/RECORD
