Metadata-Version: 2.1
Name: picbed-smtp
Version: 0.1.3
Summary: Send email with third smtp server
Home-page: https://github.com/staugur/picbed-smtp
Author: staugur
Author-email: staugur@saintic.com
License: BSD 3-Clause
Platform: UNKNOWN
